Metadata-Version: 2.1
Name: odoo12-addon-l10n-ch-payment-slip
Version: 12.0.3.3.0
Summary: Print inpayment slip from your invoices
Home-page: https://github.com/OCA/l10n-switzerland
Author: Camptocamp,Odoo Community Association (OCA)
Author-email: support@odoo-community.org
License: AGPL-3
Platform: UNKNOWN
Classifier: Programming Language :: Python
Classifier: Framework :: Odoo
Classifier: License :: OSI Approved :: GNU Affero General Public License v3
Requires-Python: >=3.5
Requires-Dist: PyPDF2
Requires-Dist: odoo12-addon-l10n-ch-base-bank
Requires-Dist: odoo (<12.1dev,>=12.0a)
